socc_plotter/__init__.py
socc_plotter/__main__.py
socc_plotter/base.py
socc_plotter/cli.py
socc_plotter/colormap.py
socc_plotter/occupancy_grid.py
socc_plotter/plotter.py
socc_plotter/schema.py
socc_plotter/socc.py
socc_plotter/socc_helper.py
socc_plotter/trajectory_utils.py
socc_plotter/transforms.py
socc_plotter/window2d.py
socc_plotter/window3d.py
socc_plotter/media/__init__.py
socc_plotter/media/car.obj
socc_plotter-0.5.0.dist-info/LICENSE
socc_plotter-0.5.0.dist-info/METADATA
socc_plotter-0.5.0.dist-info/WHEEL
socc_plotter-0.5.0.dist-info/entry_points.txt
socc_plotter-0.5.0.dist-info/top_level.txt
socc_plotter-0.5.0.dist-info/RECORD
