Metadata-Version: 2.1
Name: socc_plotter
Version: 0.5.0
Summary: Awesome socc_plotter created by AdityaNG
Home-page: https://github.com/AdityaNG/socc_plotter/
Author: AdityaNG
License-File: LICENSE
Requires-Dist: PyQt5
Requires-Dist: pyqtgraph
Requires-Dist: numpy
Requires-Dist: matplotlib
Requires-Dist: opencv-python-headless
Requires-Dist: PyOpenGL
Requires-Dist: qimage2ndarray
Requires-Dist: vedo
Requires-Dist: pydantic
Requires-Dist: pillow
Requires-Dist: pyquaternion
Provides-Extra: test
Requires-Dist: pytest; extra == "test"
Requires-Dist: coverage; extra == "test"
Requires-Dist: flake8; extra == "test"
Requires-Dist: black; extra == "test"
Requires-Dist: isort; extra == "test"
Requires-Dist: pytest-cov; extra == "test"
Requires-Dist: mypy; extra == "test"
Requires-Dist: gitchangelog; extra == "test"
Requires-Dist: mkdocs; extra == "test"
Requires-Dist: lark; extra == "test"
Requires-Dist: types-setuptools; extra == "test"
